wikicreator/__init__.py
wikicreator/cli.py
wikicreator/wikicreator_test.py
wikicreator-0.4.1.dist-info/DESCRIPTION.rst
wikicreator-0.4.1.dist-info/METADATA
wikicreator-0.4.1.dist-info/RECORD
wikicreator-0.4.1.dist-info/WHEEL
wikicreator-0.4.1.dist-info/entry_points.txt
wikicreator-0.4.1.dist-info/metadata.json
wikicreator-0.4.1.dist-info/top_level.txt
