Metadata-Version: 2.0
Name: wikicreator
Version: 0.4.1
Summary: Python Boilerplate contains all the boilerplate you need to create a Python package.
Home-page: https://github.com/MatanSilver/wikicreator
Author: Matan Silver
Author-email: matansilver@gmail.com
License: MIT license
Keywords: wikicreator
Platform: UNKNOWN
Classifier: Development Status :: 2 - Pre-Alpha
Classifier: Intended Audience :: Developers
Classifier: License :: OSI Approved :: MIT License
Classifier: Natural Language :: English
Classifier: Programming Language :: Python :: 2
Classifier: Programming Language :: Python :: 2.6
Classifier: Programming Language :: Python :: 2.7
Classifier: Programming Language :: Python :: 3
Classifier: Programming Language :: Python :: 3.3
Classifier: Programming Language :: Python :: 3.4
Classifier: Programming Language :: Python :: 3.5
Requires-Dist: Click (>=6.0)
Requires-Dist: Jinja2
Requires-Dist: PyYAML
Requires-Dist: beautifulsoup4
Requires-Dist: markdown
Requires-Dist: requests
